tmseegpy/__init__.py
tmseegpy/clean.py
tmseegpy/cli.py
tmseegpy/dataloader.py
tmseegpy/gui_launcher.py
tmseegpy/ica_nn_classifier.py
tmseegpy/ica_topo_classifier.py
tmseegpy/main.py
tmseegpy/pcist.py
tmseegpy/preproc.py
tmseegpy/preproc_vis.py
tmseegpy/run.py
tmseegpy/tep_ica_analyzer.py
tmseegpy/validate_tep.py
tmseegpy/main_gui/app.py
tmseegpy/main_gui/data_loader.py
tmseegpy/main_gui/data_viewer.py
tmseegpy/main_gui/main.py
tmseegpy/models/__init__.py
tmseegpy/models/label_encoder.pkl
tmseegpy/models/tms_eeg_classifier_spec_model.keras
tmseegpy/neurone_loader_fix/__init__.py
tmseegpy/neurone_loader_fix/lazy.py
tmseegpy/neurone_loader_fix/loader.py
tmseegpy/neurone_loader_fix/mne_export.py
tmseegpy/neurone_loader_fix/neurone.py
tmseegpy/neurone_loader_fix/util.py
tmseegpy-0.2.2.dist-info/METADATA
tmseegpy-0.2.2.dist-info/WHEEL
tmseegpy-0.2.2.dist-info/entry_points.txt
tmseegpy-0.2.2.dist-info/top_level.txt
tmseegpy-0.2.2.dist-info/RECORD
