Metadata-Version: 2.2
Name: tmseegpy
Version: 0.2.2
Summary: A pipeline for preprocessing and analyzing TMS-EEG data with a GUI developed using Streamlit
Author-email: LazyCyborg <hjarneko@gmail.com>
License: MIT
Project-URL: Homepage, https://github.com/LazyCyborg/tmseegpy
Classifier: Programming Language :: Python :: 3
Classifier: License :: OSI Approved :: MIT License
Classifier: Operating System :: OS Independent
Requires-Python: >=3.11
Requires-Dist: numpy>=1.26.0
Requires-Dist: scipy>=1.12.0
Requires-Dist: pandas>=2.0.0
Requires-Dist: mne>=1.9.0
Requires-Dist: mne-faster>=1.2
Requires-Dist: mne-qt-browser
Requires-Dist: mne-icalabel
Requires-Dist: scikit-learn>=1.4.0
Requires-Dist: tensorly>=0.8.0
Requires-Dist: tensorflow
Requires-Dist: matplotlib>=3.9.2
Requires-Dist: seaborn>=0.12.0
Requires-Dist: plotly>=5.13.0
Requires-Dist: PyQt6>=6.4.0
Requires-Dist: PyQt6-Qt6
Requires-Dist: PyQt6-sip
Requires-Dist: pyqtgraph>=0.13.0
Requires-Dist: streamlit>=1.24.0
Requires-Dist: tqdm
Requires-Dist: psutil
Requires-Dist: construct
Requires-Dist: appdirs
Requires-Dist: ipykernel
Requires-Dist: jupyter
Requires-Dist: matplotlib-inline
Requires-Dist: ipympl
Requires-Dist: PyOpenGL
Requires-Dist: pyopengl-accelerate
Requires-Dist: h5py>=3.10.0
Requires-Dist: streamlit>=1.24.0
Requires-Dist: plotly>=5.13.0
Requires-Dist: pyqtgraph>=0.13.0
